cad_ftps_client/__init__.py
cad_ftps_client/client.py
cad_ftps_client/exceptions.py
cad_ftps_client-1.0.0.dist-info/METADATA
cad_ftps_client-1.0.0.dist-info/WHEEL
cad_ftps_client-1.0.0.dist-info/licenses/LICENSE
cad_ftps_client-1.0.0.dist-info/RECORD
