Metadata-Version: 2.4
Name: cad-ftps-client
Version: 1.0.0
Summary: Secure FTPS client with mutual SSL authentication for CAD medical institutions
Project-URL: Homepage, https://github.com/neil-atr/cad-ftps-client
Project-URL: Documentation, https://github.com/neil-atr/cad-ftps-client#readme
Project-URL: Repository, https://github.com/neil-atr/cad-ftps-client
Project-URL: Issues, https://github.com/neil-atr/cad-ftps-client/issues
License: MIT License
License-File: LICENSE
Classifier: Development Status :: 4 - Beta
Classifier: Intended Audience :: Healthcare Industry
Classifier: License :: OSI Approved :: MIT License
Classifier: Programming Language :: Python :: 3
Classifier: Programming Language :: Python :: 3.12
Classifier: Topic :: Internet :: File Transfer Protocol (FTP)
Classifier: Topic :: Software Development :: Libraries :: Python Modules
Classifier: Topic :: System :: Networking
Requires-Python: >=3.12
Requires-Dist: ftputil>=5.0.0
Provides-Extra: dev
Requires-Dist: black; extra == 'dev'
Requires-Dist: flake8; extra == 'dev'
Requires-Dist: isort; extra == 'dev'
Requires-Dist: pytest-cov; extra == 'dev'
Requires-Dist: pytest-mock; extra == 'dev'
Requires-Dist: pytest>=7.0.0; extra == 'dev'
